intelliw/__init__.py
intelliw/feature.py
intelliw/prepare_env.sh
intelliw/algorithms_demo/README.md
intelliw/algorithms_demo/algorithm.py
intelliw/algorithms_demo/algorithm.yaml
intelliw/algorithms_demo/requirements.txt
intelliw/config/__init__.py
intelliw/config/cfg_parser.py
intelliw/config/config.py
intelliw/config/dataset_config.py
intelliw/core/__init__.py
intelliw/core/al_decorator.py
intelliw/core/custom.py
intelliw/core/infer.py
intelliw/core/linkserver.py
intelliw/core/pipeline.py
intelliw/core/recorder.py
intelliw/core/trainer.py
intelliw/datasets/__init__.py
intelliw/datasets/dataset_writer.py
intelliw/datasets/datasets.py
intelliw/datasets/datasource_base.py
intelliw/datasets/datasource_empty.py
intelliw/datasets/datasource_intelliv.py
intelliw/datasets/datasource_iwfactory_dr_data.py
intelliw/datasets/datasource_iwfactorydata.py
intelliw/datasets/datasource_iwimgdata.py
intelliw/datasets/datasource_large_model.py
intelliw/datasets/datasource_local_csv.py
intelliw/datasets/datasource_nlp_corpora.py
intelliw/datasets/datasource_remote_csv.py
intelliw/datasets/datasource_semantic.py
intelliw/datasets/spliter.py
intelliw/datasets/utils/iwfactory_dr_api.py
intelliw/docs/Q&A.md
intelliw/docs/README.md
intelliw/docs/instructions.md
intelliw/functions/__init__.py
intelliw/functions/data_filtering.py
intelliw/functions/feature_process.py
intelliw/functions/general.py
intelliw/functions/matrix.py
intelliw/functions/opencv.py
intelliw/functions/post.py
intelliw/functions/select_columns.py
intelliw/interface/__init__.py
intelliw/interface/batchjob.py
intelliw/interface/controller.py
intelliw/interface/customjob.py
intelliw/interface/entrypoint.py
intelliw/interface/trainjob.py
intelliw/interface/iwapi/__init__.py
intelliw/interface/iwapi/iwapp.py
intelliw/interface/iwapi/iwhandler.py
intelliw/interface/iwapi/iwmain.py
intelliw/utils/__init__.py
intelliw/utils/cGroup.py
intelliw/utils/check_algorithm_py.py
intelliw/utils/crontab.py
intelliw-2.2.6.dist-info/licenses/LICENCE
intelliw-2.2.6.dist-info/METADATA
intelliw-2.2.6.dist-info/WHEEL
intelliw-2.2.6.dist-info/entry_points.txt
intelliw-2.2.6.dist-info/top_level.txt
intelliw-2.2.6.dist-info/RECORD
