Metadata-Version: 2.4
Name: intelliw
Version: 2.2.6
Summary: An easy to start Intelligent Workshop Algorithm Framework
Home-page: http://git.yonyou.com/iuapaipaas/iw-algo-fx
Author: yonyou
Author-email: yonyou@yonyou.com
Classifier: Development Status :: 3 - Alpha
Classifier: Programming Language :: Python :: 3.6
Classifier: Programming Language :: Python :: 3.7
Classifier: Programming Language :: Python :: 3.8
Classifier: Programming Language :: Python :: 3.9
Classifier: Programming Language :: Python :: 3.10
Classifier: Programming Language :: Python :: 3.11
Classifier: Operating System :: OS Independent
Requires-Python: >=3.6
License-File: LICENCE
Requires-Dist: fastapi>=0.103.2
Requires-Dist: uvicorn[standard]>=0.22.0
Requires-Dist: python-multipart==0.0.6
Requires-Dist: gunicorn==20.1.0
Requires-Dist: PyYAML<6.1,>=5.4.1
Requires-Dist: numpy<2.0a0,>=1.15.4
Requires-Dist: pandas<2.0,>=1.1.5
Requires-Dist: absl-py>=1.4.0
Requires-Dist: requests>=2.28.2
Requires-Dist: cryptography==44.0.2
Provides-Extra: all
Requires-Dist: fastapi>=0.103.2; extra == "all"
Requires-Dist: uvicorn[standard]>=0.22.0; extra == "all"
Requires-Dist: python-multipart==0.0.6; extra == "all"
Requires-Dist: gunicorn==20.1.0; extra == "all"
Requires-Dist: PyYAML<6.1,>=5.4.1; extra == "all"
Requires-Dist: numpy<2.0a0,>=1.15.4; extra == "all"
Requires-Dist: pandas<2.0,>=1.1.5; extra == "all"
Requires-Dist: PyJWT==2.7.0; extra == "all"
Requires-Dist: scikit-learn>=0.24; extra == "all"
Requires-Dist: pycryptodome>=3.14.1; extra == "all"
Requires-Dist: apscheduler>=3.9.1; extra == "all"
Requires-Dist: eurekapy==1.0.0; extra == "all"
Requires-Dist: sqlalchemy>=1.4.0; extra == "all"
Requires-Dist: absl-py>=1.4.0; extra == "all"
Requires-Dist: requests>=2.28.2; extra == "all"
Requires-Dist: psutil==5.9.6; extra == "all"
Requires-Dist: py-spy; extra == "all"
Requires-Dist: cryptography==44.0.2; extra == "all"
Dynamic: author
Dynamic: author-email
Dynamic: classifier
Dynamic: description
Dynamic: description-content-type
Dynamic: home-page
Dynamic: license-file
Dynamic: provides-extra
Dynamic: requires-dist
Dynamic: requires-python
Dynamic: summary
